setup.py
psraw/__init__.py
psraw/base.py
psraw/endpoints.py
psraw/version.py
psraw.egg-info/PKG-INFO
psraw.egg-info/SOURCES.txt
psraw.egg-info/dependency_links.txt
psraw.egg-info/not-zip-safe
psraw.egg-info/requires.txt
psraw.egg-info/top_level.txt
test/test_endpoints.py
test/test_helpers.py